LICENSE
MANIFEST.in
README.txt
setup.py
AdobeLibManual678.egg-info/PKG-INFO
AdobeLibManual678.egg-info/SOURCES.txt
AdobeLibManual678.egg-info/dependency_links.txt
AdobeLibManual678.egg-info/top_level.txt
aanalytics2/__init__.py
aanalytics2/__version__.py
aanalytics2/aanalytics14.py
aanalytics2/aanalytics2.py
aanalytics2/config.py
aanalytics2/configs.py
aanalytics2/connector.py
aanalytics2/ingestion.py
aanalytics2/projects.py
aanalytics2/requestCreator.py
aanalytics2/token_provider.py
aanalytics2/workspace.py
test/__init__.py
test/test_configuration.py
test/test_core_analytics.py