Metadata-Version: 2.1
Name: AdobeLibManual678
Version: 4.3
Summary: abc
Home-page: 
Author: Ajay Pandey
Author-email: ajaypanday678@gmail.com
License: MIT
Keywords: adobe
Classifier: Development Status :: 5 - Production/Stable
Classifier: Intended Audience :: Education
Classifier: Operating System :: Microsoft :: Windows :: Windows 10
Classifier: License :: OSI Approved :: MIT License
Classifier: Programming Language :: Python :: 3
License-File: LICENSE
